LICENSE
MANIFEST.in
README.md
requirements.txt
setup.py
coinmarketcap/__init__.py
coinmarketcap/client.py
coinmarketcap/constants.py
coinmarketcap/core.py
coinmarketcap/utils.py
coinmarketcap_api.egg-info/PKG-INFO
coinmarketcap_api.egg-info/SOURCES.txt
coinmarketcap_api.egg-info/dependency_links.txt
coinmarketcap_api.egg-info/not-zip-safe
coinmarketcap_api.egg-info/top_level.txt
test/test_core.py