Metadata-Version: 2.1
Name: coinmarketcap-api
Version: 0.0.2
Summary: Python wrapper for coinmarketcap.com public API and private APIoffer global market data,coin data,exchanges data and more
Home-page: https://github.com/shyuntech/coinmarketcap-api
Author: hu chi
Author-email: hu.chi@qq.com
License: Apache v2.0 License
Keywords: cryptocurrency,API,coinmarketcap
Platform: UNKNOWN
Classifier: License :: OSI Approved :: Apache Software License
Classifier: Development Status :: 5 - Production/Stable
Classifier: Intended Audience :: Developers
Classifier: Programming Language :: Python
Classifier: Programming Language :: Python :: 2.7
Classifier: Programming Language :: Python :: 3.6
Classifier: Topic :: Software Development :: Libraries :: Python Modules
